dysweep/__init__.py
dysweep/console.py
dysweep/helper.py
dysweep/parallel.py
dysweep/utils.py
dysweep/wandbX.py
dysweep-0.1.6.dist-info/LICENSE
dysweep-0.1.6.dist-info/METADATA
dysweep-0.1.6.dist-info/WHEEL
dysweep-0.1.6.dist-info/entry_points.txt
dysweep-0.1.6.dist-info/top_level.txt
dysweep-0.1.6.dist-info/RECORD
